License.md
MANIFEST.in
Readme.md
dev-requirements.txt
setup.py
clinch/__init__.py
clinch/app.py
clinch/app_test.py
clinch/arg.py
clinch.egg-info/PKG-INFO
clinch.egg-info/SOURCES.txt
clinch.egg-info/dependency_links.txt
clinch.egg-info/top_level.txt